[
    {
        "id": "1",
        "title": "لماذا نزل القرآن عربيا",
        "name": "الشيخ محمد الشعراوي",
        "iframeData": "kYaFq_5FTdE",
        "image": "images/image 3.jpg"
    },
    {
        "id": "2",
        "title": "الطريق إلي الله",
        "name": "الشيخ محمود شعبان",
        "iframeData": "iW65Rt5f_u8",
        "image": "images/image5.jpg"
    },
    {
        "id": "3",
        "title": " قصص عجيبة عن بني إسرائيل ",
        "name": "الشيخ محمد الحويني",
        "iframeData": "4lvdN8appwU",
        "image": "images/image5.png"
    },
    {
        "id": "4",
        "title": "فترة الخطوبة",
        "name": "المهندس أيمن عبدالرحيم",
        "iframeData": "aX_xHR9HZo0",
        "image": "images/image6.jpg"
    },   
     {
        "id": "5",
        "title": "موقف المسلم من الفتن",
        "name": "الشيخ عبدالعزيز الطريفي",
        "iframeData": "HkROyT9wlhI",
        "image": "images/image8.jpg"
    },
    {
        "id": "6",
        "title": "مش هتبطل صلاة ",
        "name": "الشيخ أمير منير",
        "iframeData": "qZnOPl8UqK0",
        "image": "images/image7.jpg"
    }
]